clivo/__init__.py
clivo/cli.py
clivo-0.4.0.dist-info/LICENSE
clivo-0.4.0.dist-info/METADATA
clivo-0.4.0.dist-info/WHEEL
clivo-0.4.0.dist-info/top_level.txt
clivo-0.4.0.dist-info/RECORD
