Metadata-Version: 2.1
Name: clivo
Version: 0.4.0
Summary: General command line interface to control object properties in real time and trigger events
Home-page: https://github.com/ovinc/clivo
Author: Olivier Vincent
Author-email: ovinc.py@gmail.com
Keywords: command,line,interface
Classifier: Programming Language :: Python :: 3
Classifier: Programming Language :: Python :: 3.6
Classifier: Programming Language :: Python :: 3.7
Classifier: Programming Language :: Python :: 3.8
Classifier: Programming Language :: Python :: 3.9
Classifier: License :: OSI Approved :: BSD License
Classifier: Operating System :: OS Independent
Requires-Python: >=3.6
License-File: LICENSE
